<?xml version="1.0" ?><review><id>72265</id><useful>1</useful><authorId>1791170</authorId><authorName>سامي الشمري</authorName><authorNOR>10</authorNOR><subject> الجمعية السعودية الخيرية لمرضى الزهايمر في الرياض</subject><catogary> خدمات عامة وحكومية </catogary><rate>5</rate><body>جمعية خيرية ممتازة انا رحت عندهم عندنا احد من الاهل مصاب بهذا المرض الله لا يبلي احد فيه وعندهم نصايح وطرق التعامل وهي جمعية تعتمد كليا على التبرعات من اهل الخير وكلتزمين بالمواعيد والمتابعه للمرضي بشكل جيد</body><path>D:\work\om\data\p\saudi-alzheimer-disease-association-riyadh\index.html</path><city>riyadh</city><date>2013-08-08 10:41:03.52 UTC</date></review>