<?xml version="1.0" ?><review><id>72448</id><useful>0</useful><authorId>1791522</authorId><authorName>فيصل الفيصل</authorName><authorNOR>1</authorNOR><subject> عبدرحمن المطيري في الرياض</subject><catogary> أزياء </catogary><rate>5</rate><body>حلو في كل شي من ملابس داخلية من جزم من قمصان نوم من غتر و أشمغة وأفضل شي في المحل العامل الي فيه هندي أسمه ناصر والله نككككككته ولا تمل من السواليف معلة فللللللة ا</body><path>D:\work\om\data\p\abd-rehman-al-muteri-riyadh\index.html</path><city>riyadh</city><date>2013-08-11 10:32:23.849 UTC</date></review>