<?xml version="1.0" ?><review><id>72650</id><useful>3</useful><authorId>1791321</authorId><authorName>Suliman Bin Taher</authorName><authorNOR>15</authorNOR><subject> الدانوب في جدة</subject><catogary> تسوق </catogary><rate>4</rate><body>هايبر ماركت رائع بديكوراته وطريقة عرض جميلة قسم المخابز والحلويات مبهر ارتاح كثير في التسوق فيه الاسعار بعضها مرتفع عن الامكان الاخرى والبعض جيد يمتاز باستيراد اصناف محددة من بريطانيا وامريكا لديه التنوع الكبير من المنتجات بعض الفروع كالصيرفي مول يقوم تقديم وجبات غدائية بأسعار رمزية</body><path>D:\work\om\data\p\danube-jeddah\index.html</path><city>jeddah</city><date>2013-08-12 10:36:05.594 UTC</date></review>