<?xml version="1.0" ?><review><id>47666</id><useful>0</useful><authorId>1751906</authorId><authorName>بندر الشريف</authorName><authorNOR>31</authorNOR><subject> مكتبة جسور في جدة</subject><catogary> مقاهي وكوفي شوب </catogary><rate>4</rate><body>تمتاز جسور بموقعها اولا فحي الحمرا من ارقى الأحياء بجده ويعتبر الموقع نقطة التقاء للجميع وبما انه حضرنا فيه اجتماع جيران جده وجدت ان الموقع حلو جدا أضافه الي ان الكتب فيه متوفره وزي ما سمعت وشفت ان الكتب فيه متوفره في جميع العلوم بس عيبوا حاجتين اولا ضيق المكان واللي ان شاء الله اكيد في المستقبل وبعد تطور نشاطهم راح ينقلوا مكان اكبر منه والشئ الثاني عدم توفر المواقف للسيارات ومميزاته كمان بشاشة مواضفيه وحسن تعاملهم مع الزوار ...</body><path>D:\work\om\data\p\bridges-bookstore-jeddah\index.html</path><city>jeddah</city><date>2012-08-20 10:34:59.444 UTC</date></review>