<?xml version="1.0" ?><review><id>12970</id><useful>0</useful><authorId>1736369</authorId><authorName>ريان العبدالله</authorName><authorNOR>5</authorNOR><subject> واحة جدة للعلوم الترفيهية في جدة</subject><catogary> ترفيه </catogary><rate>5</rate><body>المكان اللي جمع بين متعة العلم والتعليم الممتع تحت سقف واحد تقدم واحة جدة للعلوم سبعة انواع من الترفية الهادف في سبع صالات وتجعل التعليم حق مشاع للجميع .كل ذلك بأسلوب ترفيهي مشوق وجذاب لازم كل فترة ناخذ الصغار ونروح للاندلس عشان هـ المركز الرائع منها نتسوق ومنها العيال يتمشو وينبسطو ويتعلمو كمان الاسعار مناسبة والخدمات حلوة يستحفق الزيارة .</body><path>D:\work\om\data\p\jeddah-science-oasis-jeddah\index.html</path><city>jeddah</city><date>2012-08-20 10:38:04.423 UTC</date></review>