<?xml version="1.0" ?><review><id>25926</id><useful>1</useful><authorId>1743468</authorId><authorName>ريم عبد الله 2012</authorName><authorNOR>93</authorNOR><subject> اميرة لتاجير السيارات في الرياض</subject><catogary> سيارات </catogary><rate>5</rate><body>اخواني يستاجرون من عندهم سيارات بس مو بالمستوي المطلوب السيارات قديمة وما ينعملها الصيانة وكثيرة الخراب الاسعار عادية بس العاملين ما يتعاملون بالطف مع الزباين لا دائما مزعجين</body><path>D:\work\om\data\p\amira-rent-a-car-2-riyadh\index.html</path><city>riyadh</city><date>2012-08-20 10:34:18.74 UTC</date></review>