<?xml version="1.0" ?><review><id>39242</id><useful>0</useful><authorId>1746705</authorId><authorName>الاء بنت حافظ</authorName><authorNOR>15</authorNOR><subject> تويز ار اس في الرياض</subject><catogary> تسوق </catogary><rate>4</rate><body>ممتااااااز جدا للاطفال يوجد جميع الالعاب لكل الاعمار والمناسبات ويوجد من ناحية التعليم للاطفال واستخدام لوسائل مساعدة الطفل على النمو والتطور</body><path>D:\work\om\data\p\toys-r-s-riyadh\index.html</path><city>riyadh</city><date>2012-08-20 10:42:20.637 UTC</date></review>