<?xml version="1.0" ?><review><id>73063</id><useful>1</useful><authorId>1785146</authorId><authorName>Joody Afndm 2012</authorName><authorNOR>68</authorNOR><subject> معهد الفنار المتميز النسائي للتدريب في جدة</subject><catogary> تعليم </catogary><rate>4</rate><body>معهد الفنار يعدي دورات للقدرات والتحصيلي يفيدهم يعطي دروات للحاسب انا اخذت من عندهم دوره اكسل بس نسيت السعر بزبط كان عباره عن ٤ ساعات ناخذ شهاده من معهد كان لكل طالبه جهاز تشتغل وتطبق مع الاستاذه بصراحه استفدت استمتعت معهد ممتاز اعطاني شهاده بعد ماخلصنا بربع ساعه بس مشكله كان في بدايه يجمع اعداد هي الي جلسنا انتظرنا فيها اتذكر يعطو دورات الاكسل يوم الخميس الساعه ١٠ مادري اذا غيرها بالتوفيق للجميع ودي</body><path>D:\work\om\data\p\al-fanar-special-women-center-for-training-jeddah\index.html</path><city>jeddah</city><date>2013-08-16 10:33:01.150 UTC</date></review>