<?xml version="1.0" ?><review><id>43427</id><useful>0</useful><authorId>1753050</authorId><authorName>هديل قاهر</authorName><authorNOR>7</authorNOR><subject> هايبر بنده في الرياض</subject><catogary> مأكولات وتسالي </catogary><rate>4</rate><body>صراحة هايبر بنده والبنده من افضل الاماكن والسوبر ماركات اللي بنتسوق فيها احسن وافضل من باقي السوبر ماركت وبتلاقي فيه كل اللي عايز تشتريه ومنتجاتهم ممتازة ومضمونة وبالذات في الخضار والفواكه احنا ما ناخذها الا منهم ،، ومن ناحية النظافة واصطاف العمل رائعين وجزا الله كل خير من يعمل في هذا المكان ،، لكن كمان ياجماعة للامانه برضو من تجو تدفعوا الحساب وتطلعوا احسن تراجعوا فواتيركم لانو مرات وحصلت معانا كم مرة بتلاقي حاجات ما تكون اشتريتها ونازلة في الفاتورة امكن والله اعلم سهوا بس دي للامانه العامة ،،</body><path>D:\work\om\data\p\hyper-panda-2-riyadh\index.html@page=2.html</path><city>riyadh</city><date>2012-08-20 10:37:41.516 UTC</date></review>