<?xml version="1.0" ?><review><id>43870</id><useful>0</useful><authorId>5921</authorId><authorName>هدى العقرباوي 2011 2012</authorName><authorNOR>336</authorNOR><subject> روتانا كافيه في عمان</subject><catogary> مقاهي وكوفي شوب </catogary><rate>4</rate><body>كافيه روتانا من الكافيهات الحلوه يلي ممكن الواحد يروحها بوئت فترة المسا لانو الجو كتير حلوووو وبكووون عجئه والئعده حلوه كتيررررررررر .............وبيئدم منيو زاكي انا جربت الحلويات متل التشيز كيك والتيرامسو كتير زاكيين وكنت اشوف الطلبات يلي الناس بيلبوها منظرها كتير زاكي ومرتب بس ما بعرف كيف النكهه والمكان طبعا بجيب فنانيين وبيعمل فعاليات حلوه خدمة الفاليه موجوده الاسعار غاليه كتيرررررررررررر الخدمة منيحة والموظفين كتير بشوشيين</body><path>D:\work\om\data\p\rotana-cafe-amman\index.html</path><city>amman</city><date>2012-08-20 10:40:39.113 UTC</date></review>