<?xml version="1.0" ?><review><id>68242</id><useful>0</useful><authorId>1749972</authorId><authorName>Huwaida Chemat 2012</authorName><authorNOR>84</authorNOR><subject> انتي انز في الرياض</subject><catogary> مطاعم </catogary><rate>5</rate><body>آنتي آنز اسم رائد في عالم المخبوزات و الفطائر العالمية اللذيذة... هو اقرب من أن يكون مخبزا اكثر من كونه مطعم حيث لا توجد هناك جلسات عائلية ولا صالة ألعاب للاطفال... لكن الفطائر عندهم جنان وطعمها رائع... عندهم فطائر بالسمسم وفطائر سادة وفطائر باللوز وفطائر بالشوكولاته وغيرها ... وانا احب فطائر السمسم... تقدم إليك حارة وشهية... هذا بالاضافة إلى المشروبات الساخنة والباردة... كما أن هناك وجبات خاصة للأطفال ... فطائر صغيرة الحجم ومشروبات خاصة لهم... اما اسعارهم فهي مناسبة وليست بالغالية... فالمطعم مشهور عالميا والأسعار على مستوى جيد... انصح كل من يزور برج المملكة أو المولات الشهيرة في الرياض زيارة فرع آنتي آنز وشراء فطيرة ومشروب تشبعك طول الطريق...</body><path>D:\work\om\data\p\aunte-anns-riyadh\index.html</path><city>riyadh</city><date>2013-05-20 10:34:33.737 UTC</date></review>