<?xml version="1.0" ?><review><id>70052</id><useful>0</useful><authorId>1780663</authorId><authorName>اميرة النبهان</authorName><authorNOR>11</authorNOR><subject> بيت الشواية في الرياض</subject><catogary> مطاعم </catogary><rate>5</rate><body>ان هذا المطعم المفضل لدي فطعامه لذيذ جداً ولا يقاوم وخدمته ممتازة وبسرعة جيدة واصح جميع العالم بأن يجربوا طعامه الفاخر السعر رايع ومناسب جدا و متناول الجميع</body><path>D:\work\om\data\p\shawaya-house-19-riyadh\index.html</path><city>riyadh</city><date>2013-07-20 10:41:18.48 UTC</date></review>