<?xml version="1.0" ?><review><id>70157</id><useful>0</useful><authorId>1786411</authorId><authorName>Muna Omar</authorName><authorNOR>5</authorNOR><subject> مسجد الراجحي في الرياض</subject><catogary> خدمات عامة وحكومية </catogary><rate>5</rate><body>مسجد جمييل ونظيف ومرتب ديكوره من جوا حلوو واسع يشيل ناس كثيييييير وحتى مع الزحمه ماتحسون بالحر لان تكيفيه رااااائع ان شاء الله صلاه العيد راح تكون فيه بأذن الله ..</body><path>D:\work\om\data\p\al-rajhi-mosque-riyadh\index.html</path><city>riyadh</city><date>2013-07-20 10:33:35.748 UTC</date></review>