<?xml version="1.0" ?><review><id>42469</id><useful>0</useful><authorId>1751949</authorId><authorName>Marwan Habib</authorName><authorNOR>1</authorNOR><subject> مطعم الخليج الصيني في الخبر</subject><catogary> مطاعم </catogary><rate>4</rate><body>ممتاز من وقت ما غيرو الشف بس المن كتير كبير وبحير لازم يزغرو ويحسنو، زرت أكتر من 5 مرات وكل مرة بكون أطيب من مرة.</body><path>D:\work\om\data\p\gulf-chinese-restaurant-khobar\index.html</path><city>khobar</city><date>2012-08-20 10:37:08.215 UTC</date></review>