<?xml version="1.0" ?><review><id>59785</id><useful>0</useful><authorId>1772329</authorId><authorName>ahmad Asmar</authorName><authorNOR>19</authorNOR><subject> المنقل تشكن تكا في اربد</subject><catogary> مطاعم </catogary><rate>4</rate><body>هو المنقل من اطيب المطعم الموجوده باربد والنظافه لا توصف والتعامل مرتب والخبز الي بعملو بشهي انا هادا المطعم كتير بفوت عليه اسعاره ممتازه جدا فتت عليه انا وشباب مره وطلبنه كباب ما كان مستوي كتير بس انا ما غيرت نظرتي بالمطعم ولاهسه بحب افوت عليه .</body><path>D:\work\om\data\p\al-manqal-chicken-tikka-irbid\index.html</path><city>irbid</city><date>2012-12-20 10:33:18.796 UTC</date></review>