<?xml version="1.0" ?><review><id>29451</id><useful>0</useful><authorId>1746423</authorId><authorName>Aya Hamra</authorName><authorNOR>5</authorNOR><subject> سيتي مول في عمان</subject><catogary> تسوق </catogary><rate>4</rate><body>سيتي مول مكان جميل تروح علية بعد فطور... موجود فية كافيه و مطاعم و محلات ملابس يعني واحد بروح بشتري اواعي للعيد و جو كتير بكون حلو بتحس حالك جد برمضان و مش لازم ننسى سينما حلو واحد يسلى وقته بعد الفطور</body><path>D:\work\om\data\p\city-mall-amman\index.html@page=4.html</path><city>amman</city><date>2012-08-20 10:35:49.446 UTC</date></review>