<?xml version="1.0" ?><review><id>56366</id><useful>0</useful><authorId>1741309</authorId><authorName>فراس قاسم 2011</authorName><authorNOR>370</authorNOR><subject> مركز آي آرز في عمان</subject><catogary> خدمات </catogary><rate>3</rate><body>ايجابيات المكان: المكان كتير واسع وحلو ومناسب جدا للاجتماعات والندوات او المؤتمرات قليلة العدد يقدم المشروبات الساخنة والباردة زي ماشفت وبعتمد على نظام البوفيه المفتوح في تقديم الطلبات الخدمة كانت ممتازة حقيقة وتلبية الطلبات كانت سريعة الديكور جميل ومناسب وحلو ولكن ترتيب الطاولات ربما لم يكن جيدا لكثرة العدد الموجود بالرغم انه مهيئ لعدد اكبر من الحضور الكراسي كانت مريحة نوعا ما اسعار الطلبات عنده حسبما سمعت (صدقا انا لم اسئل) انما سمعت انها مناسبة واضح ان الهدوء مايميز المكان والنظافة ممتازة حسبما رايت سلبيات المكان: حجم الطاولات صغيرة الحجم حجم المكان او ترتيب المكان لايناسب الاجتماعات كثيرة الحضور؟ بمختصر الكلام: ازا اتيحت لي الفرصة من جديدة لزيارة المكان لن اتردد</body><path>D:\work\om\data\p\irz-business-centre-amman\index.html</path><city>amman</city><date>2012-11-20 10:37:50.209 UTC</date></review>