<?xml version="1.0" ?><review><id>56435</id><useful>3</useful><authorId>1766734</authorId><authorName>روضة تركي</authorName><authorNOR>38</authorNOR><subject> الصنوبرة في جدة</subject><catogary> مطاعم </catogary><rate>3</rate><body>بسم الله الرحمن الرحيم مطعم الصنوبرة الموقع بالتحديد جدة – شارع صاري – مركز هاشم مقابل مكتبة جرير – يتميز بالمأكولات. اللبنانية انعزمت فيه مرة مع زوجى المطعم يتكون من دورين عند دخولنا استقبالنا موظف الاستقبال بالترحيب بينا واخذنا الى مكان العائلات ولكن ديكور المطعم عادية وجلسات شبه مغلقه وصغير و به بعض الرسومات على الجدران وبعد ما جلسنا حضر لنا قائمة الطعام وقد طلبنا مابين المشويات الشرقية التقليدية والمأكولات الغربية دون نسيان المقبلات التي اشتهر بها المطبخ اللبناني خصوصاً والشامي عموماً الأطباق الجانبية من مقبلات وحساء وعصيرات كانت ممتازة الأطباق الرئيسية لاباس بها أما الاسماك فلا أنصح بها أما المشويات فجيدة جداً جداً جودة الطعام كما قالت المشويات والمقبلات رائعة رائحة التوابل ممتازة وذو رائحة رائعة طريقة تقديم الطعام رائعة يقدم المشويات على خبز وبه بعض ورقات البقدونس والبصل المشوي والطماطم بالنسبة للسعر الفاتورة كانت 115 ريال يضاف 10 % رسوم خدمة على الفاتورة اعتقد رخيص بالنسبة اذا قارن للمطاعم الاخرى خدمة الزبائن فوق الممتاز فى الاستقبال وفى تقديم الطعام اسلوب مهذب من جميع الموظفين بالمطعم النظافة ممتازة تتوفر خدمة الاصطفاف للسيارات امام المطعم فقط من وجهة نظرى المطعم يحتاج الى توسيع او تغير المكان الى اكبر • انصح االذى يحب المشويات اللبنانية والمقبلات بزيارة المطعم • فهو فعلا يستحق من جودة طعام المشويات والمقبلات والخدمة ومعاملة</body><path>D:\work\om\data\p\sunobra-jeddah\index.html</path><city>jeddah</city><date>2012-11-20 10:41:54.334 UTC</date></review>