<?xml version="1.0" ?><review><id>34596</id><useful>0</useful><authorId>1748737</authorId><authorName>Nisreen Rabba</authorName><authorNOR>6</authorNOR><subject> مطعم راجعين في عمان</subject><catogary> مطاعم </catogary><rate>5</rate><body>للتمتع بالاطلالة الخلابة على جبال عمان توجه لراجعين حيث الجلسات الرائعة ولمحبي الاراجيل رح تنبسطو .. القعدة على بلكونة المطعم روووووووووووعة ولا الخدمة المميزة والاحلى منيو الاكل يا سلام اطلب واتمنى وراجعين يبستنى</body><path>D:\work\om\data\p\rajeen-restaurant-amman\index.html</path><city>amman</city><date>2012-08-20 10:40:20.587 UTC</date></review>