<?xml version="1.0" ?><review><id>50538</id><useful>0</useful><authorId>1758272</authorId><authorName>كامري الكامري</authorName><authorNOR>39</authorNOR><subject> السعودي الألماني في الرياض</subject><catogary> خدمات طبية </catogary><rate>5</rate><body>اشهر من نار على علم هذا المستشفى مرة روعة كل التخصصات تلاقيها فيه والاهم من كذا ان الاطباء الى موجودين فيه كلهم قمة وكفائة وانا بصراحة ما ارتاح غير بالتعامل معاهم وللفحوصات حقتهم لا ااحس انا سليمة ودقيقة مرة اما بالنسبة للعاملين عندهم الله الابتسامة ما تفارق وجوهم انا انصح الكل بالتعامل معاهم</body><path>D:\work\om\data\p\saudi-german-riyadh\index.html</path><city>riyadh</city><date>2012-08-20 10:41:04.231 UTC</date></review>