<?xml version="1.0" ?><review><id>69682</id><useful>0</useful><authorId>1772341</authorId><authorName>نور حسن</authorName><authorNOR>26</authorNOR><subject> تشيليز في الرياض</subject><catogary> مطاعم </catogary><rate>5</rate><body>المطعم راقي جدا مع العلم ان اسعارهم غالية بس القائمة حقتهم فيها اصناف مرة تفتح النفس والحين بالرمضان يعملون عروض مرة حلوة ومشجعة المشلكة عندهم انك لازم تحجز عندهم بوقت كافي ويالله يالله تلاقي عندهم مكان فاضي احب اكل عندهم البطاطس معالجبن شي ما ينوصف انصحكم بالتجربة النظافة روعة والجلسات تهبل جربوهم</body><path>D:\work\om\data\p\chilis-riyadh\index.html</path><city>riyadh</city><date>2013-07-20 10:35:38.695 UTC</date></review>