<?xml version="1.0" ?><review><id>3363</id><useful>6</useful><authorId>2509</authorId><authorName>محمد الديري</authorName><authorNOR>41</authorNOR><subject> مؤسسة إنجاز في عمان</subject><catogary> خدمات عامة وحكومية </catogary><rate>5</rate><body>أنا تطوعت قبل سنتين مع مؤسسة انجاز، و كانت تجربة رائعة، استفدت منها كتير،لأنه المتطوع من خلال تدريبه للطلاب بتعلم أشياء جديدة. وبالنسبة لفريق مؤسسة انجاز كانوا متعاونين جدا مع المتطوعين.</body><path>D:\work\om\data\p\injaz-amman\index.html</path><city>amman</city><date>2012-08-20 10:37:47.842 UTC</date></review>