<?xml version="1.0" ?><review><id>68605</id><useful>0</useful><authorId>1784106</authorId><authorName>Anas Tawfiq</authorName><authorNOR>6</authorNOR><subject> سيتي مول في عمان</subject><catogary> تسوق </catogary><rate>2</rate><body>انا بصراحه برتاح في مكة مول اكثر بس بعجبني بالسيتي مول المطاعم و الكفيات و أهم شي جراند سينما بس مشكلتوا مش نظيف كثير وبتشوف الموضفين قاعدين جنب الحمام ورافعين صوتهم وكمان أهم اشي بخزي في السيتي مول ولي شفتوا مبارح الأدراج الكهربية كانت أكثرها خربانه يعني اللي معاه عرباية اطفال مشكلة مظطر يطلع من المصاعد</body><path>D:\work\om\data\p\city-mall-amman\index.html</path><city>amman</city><date>2013-06-20 10:35:48.207 UTC</date></review>