<?xml version="1.0" ?><review><id>68632</id><useful>0</useful><authorId>1784186</authorId><authorName>سعيد ساري</authorName><authorNOR>2</authorNOR><subject> صيدلية سلمى القسوس في عمان</subject><catogary> خدمات طبية </catogary><rate>5</rate><body>اروع الصيدليات التي مرت على من حيث التعامل ومن حيث النظافة والترتيب اهتمام عالي بالمرضى تامين جميع احتياجات المرضى من الادويه بشكل سريع تميز في الاداء ومصداقيه عاليه وشفافيه</body><path>D:\work\om\data\p\salma-g-pharmacy-amman\index.html</path><city>amman</city><date>2013-06-20 10:40:58.291 UTC</date></review>