<?xml version="1.0" ?><review><id>68640</id><useful>4</useful><authorId>2405</authorId><authorName>سوسن الخضير</authorName><authorNOR>54</authorNOR><subject> مردكوش في عمان</subject><catogary> مطاعم </catogary><rate>4</rate><body>اليوم انا وزملائي بالعمل جربنا هادا المحل .. بالنسبة للطعام كان متنوع متل الكبة و البيتزا و التبولة و السبانخ وغيرها كتير التجربة كانت ممتازة ورح ارجع اطلب من عنده دايما . جودة الطعام بعطيه 8/10 نظافة الطعام 10/10 بالنسبة للسويتس كانت اكتر من رائعة .. زاكية وخفيفة عالمعدة يعني كان مذاقها متل مذاق الحلويات في مكاني المفضل لورين بنصحكم تجربوه</body><path>D:\work\om\data\p\mardakoosh-2-amman\index.html</path><city>amman</city><date>2013-06-20 10:39:06.979 UTC</date></review>