<?xml version="1.0" ?><review><id>5537</id><useful>1</useful><authorId>12018</authorId><authorName>سعد القحطاني</authorName><authorNOR>6</authorNOR><subject> ميراج في الرياض</subject><catogary> مطاعم </catogary><rate>3</rate><body>الحقيقة انا ما حبيته انا مرة عزمت الاهل فيه وطلعت الفاتورة اكثر من 600 ريال والخدمة بس 85 ريال هو اكلهم وشوربتهم حلوة ولكن عندما جيت لحالي وطلبت بقيمة 60 ريال قالي لا لازم فوق 100 زين انا لحالي يعني اخذ اكل وارميه التعامل سيء اكثر ما يروح لها البنات اللي ما يعرفون قيمة الفلوس وديكوره ايضا حلوة ولكن غير مبهر انا ما احب المطعم اللي ما يقدر زباينه بعض الاحيان اذا كان الطعم جيد ولكن التعامل ممتاز تحبهم اكثر من اللي طعمه جيدجدا وتعامله غير لائق</body><path>D:\work\om\data\p\mirage-2-riyadh\index.html</path><city>riyadh</city><date>2012-08-20 10:39:21.728 UTC</date></review>