<?xml version="1.0" ?><review><id>59328</id><useful>0</useful><authorId>1767062</authorId><authorName>Jomaanh Baabbad 2012</authorName><authorNOR>172</authorNOR><subject> ادمز في الرياض</subject><catogary> أزياء </catogary><rate>5</rate><body>هي ازياء واطفالية روووعة موضاتهاا جمييييلة حيل ..ونعومة ذات الماااركات العاليا .. وايضا مكان نظيف ورااااقي حييييل .. وانصح زياارتهاا جداا رووووعة ملابسهااا.. جداا جميييلة وشكرااا</body><path>D:\work\om\data\p\adams-3-riyadh\index.html</path><city>riyadh</city><date>2012-12-20 10:32:35.213 UTC</date></review>