<?xml version="1.0" ?><review><id>59404</id><useful>0</useful><authorId>1769270</authorId><authorName>نمر فوزان</authorName><authorNOR>40</authorNOR><subject> مطعم النافورة في الرياض</subject><catogary> مطاعم </catogary><rate>5</rate><body>من اقدم المطاعم حقت الشاورما طعمها مرة خطر الاسعار عندهم زينة النظافة يبغالها شوية بس بشكل عام زين وانصح الجميع بالتجربة</body><path>D:\work\om\data\p\al-nafoura-restaurant-2-riyadh\index.html</path><city>riyadh</city><date>2013-01-20 10:33:23.712 UTC</date></review>