<?xml version="1.0" ?><review><id>59945</id><useful>0</useful><authorId>1739302</authorId><authorName>احمد سيد</authorName><authorNOR>7</authorNOR><subject> مطاعم ريدان في جدة</subject><catogary> مطاعم </catogary><rate>5</rate><body>اكلت فيه المندى والمظبى بس كان سفرى بسبب الزحام المحل جيد من حيث الترتيب والنظافة ويوجد لديه المضغوط ايضا الخدمة فيه ممتازة بالنسبة للزحام انصحك بالمندى ولكن مشكلة المطعم الاصطفاف فقط انصحك بزيارته</body><path>D:\work\om\data\p\raidan-restaurants-jeddah\index.html</path><city>jeddah</city><date>2013-01-20 10:40:19.60 UTC</date></review>