<?xml version="1.0" ?><review><id>65628</id><useful>0</useful><authorId>1333809</authorId><authorName>tariq al-zahrani</authorName><authorNOR>4</authorNOR><subject> مطعم الرومنسية في الخبر</subject><catogary> مطاعم </catogary><rate>3</rate><body>أنا جربت الرومانسية اللي بالرياض ،، أما هنا بالدمام والخُبر ماكنت أدري أن لهم فروع ،، لكن عموما ً أكلهم بصراحة نظيف وأفضل مطعم يسوي الرز والدجاج واللحم والشغلات هذي بصراحة ،،، وبالهنا للجميع *_*</body><path>D:\work\om\data\p\al-romanseya-restaurant-khobar\index.html</path><city>khobar</city><date>2013-04-20 10:33:42.521 UTC</date></review>