<?xml version="1.0" ?><review><id>65875</id><useful>0</useful><authorId>1780703</authorId><authorName>abo osama Al-tellawi</authorName><authorNOR>1</authorNOR><subject> العثيم مول في الرياض</subject><catogary> تسوق </catogary><rate>3</rate><body>بشكل عام التسوق في العثيم جيد إلى حد ما هناك بعض المساوئ حيث الأسعار غير مستقرة تحصل بعض التخفيضات لفترة قصيرة جداً وتستمر الحملة الدعائية لفترة طويلة أي معظم الأصناف التي توضع في الحملة تنتهي بسرعة البرق واللي يدخل السوق يتورط أماكن الترفيه في العثيم مول مرتفعة بعض الشيئ</body><path>D:\work\om\data\p\othaim-mall-riyadh\index.html</path><city>riyadh</city><date>2013-04-20 10:39:47.391 UTC</date></review>