<?xml version="1.0" ?><review><id>27232</id><useful>1</useful><authorId>1745167</authorId><authorName>احمد العنزي</authorName><authorNOR>5</authorNOR><subject> العثيم مول في الرياض</subject><catogary> تسوق </catogary><rate>4</rate><body>نعم انا اشتري الملابس للعائله دائما من سوق العثيم مول لقربه الجغرافي لي واسعارهم المناسبه وملبسهم الجميله والمميزه ودائما تجد الافظل لديم لذلك انصح بالزياره لهذه السوق الجميل</body><path>D:\work\om\data\p\othaim-mall-2-riyadh\index.html@page=2.html</path><city>riyadh</city><date>2012-08-20 10:39:47.53 UTC</date></review>