<?xml version="1.0" ?><review><id>20796</id><useful>0</useful><authorId>1740098</authorId><authorName>اسووله دلووعه ماما السحمان</authorName><authorNOR>14</authorNOR><subject>  ايكيا  في الرياض</subject><catogary> أثاث ولوازم منزلية </catogary><rate>5</rate><body>ايكيا احسن محل بالرياض لانه فيه كل الاشياء الي تبينها ادوات المنزل او الاجهزه الاكترونيه و اثاثهم الاكثر من الرائع والالعاب حللوه وانا اشكر ايكيا ^_^</body><path>D:\work\om\data\p\ikea-riyadh\index.html@page=2.html</path><city>riyadh</city><date>2012-08-20 10:37:45.933 UTC</date></review>