<?xml version="1.0" ?><review><id>66049</id><useful>0</useful><authorId>1780958</authorId><authorName>عبير الهندي</authorName><authorNOR>1</authorNOR><subject> القنديل الذهبي في الرياض</subject><catogary> مطاعم </catogary><rate>5</rate><body>اوه احلى برستد عندي طعمه حلو بالمررة و ما يتاخر الطلب يجيك وهو حار و مستوي بس مثل ما قال اخوي لازم تفكون الكيس (ما تخلونه ينكتم ) لانه اذا انكتم يتغير طعمه وشكرا و اتمنى انكم استفدتوا مني انصح الجميع به</body><path>D:\work\om\data\p\al-qandil-al-thabi-riyadh\index.html</path><city>riyadh</city><date>2013-04-20 10:33:31.10 UTC</date></review>