<?xml version="1.0" ?><review><id>70300</id><useful>0</useful><authorId>1752853</authorId><authorName>Khiyar Saeed</authorName><authorNOR>6</authorNOR><subject> مطعم فابيانو في الرياض</subject><catogary> مطاعم </catogary><rate>4</rate><body>اذا كنت من محبي الباستا أو حتى مالك أي علاقه بالباستا و تبي يكون لك علاقه جديده معها ما عليك الا بالمطعم الايطالي فابيانو روووعه في كل شي خصوصا النظام الأمريكي ( self service ) .... النظافه و الديكور على مستوى عالي يوجد جبلسات خارجيه و مواقف ... يستخدمون البطاقه الممغنطه للطلبات و الدفع خاصه بمطعمهم يتم اعطائها لك عند الدخول اضاعتها يعني 250 ريال غرامه ...</body><path>D:\work\om\data\p\vapiano-restaurant-riyadh\index.html</path><city>riyadh</city><date>2013-07-20 10:42:26.622 UTC</date></review>