<?xml version="1.0" ?><review><id>70781</id><useful>1</useful><authorId>1751823</authorId><authorName>Oscar Yagami</authorName><authorNOR>17</authorNOR><subject> شارلوت كيك في جدة</subject><catogary> مأكولات وتسالي </catogary><rate>5</rate><body>خدمة راااااااااااااااائعه! تجربتي مع شارلوت كانت قبل اسبوع. كان عندي مناسبة و اشتريت من عندهم كيكة ايسكريم الكوكيز! كانت رائعه. اشتريت من عندهم كمان علبة صغيره فيها تشكيلة كب كيك ب 45 ريال صراحه الشكل و فكرة التقديم كانت مميزة و الطعم كان بجودة الشكل و اكتر كمان. اول ما دخلت المكان استقبلني موظف فلبيني و كان سوالي بس ايش انواع الكيك اللي عندكم. اعطاني نبذة كامله عن كل شي يقدموه و انو تخصصهم الحلويات الايطالية باسلوب راقي جدا! مع انو كان يقدر يعطيني المنيو اللي كانت على الطاوله قدامو! في الاخير اعطاني كرت المحل و قلي دواماتهم و اني اقدر اتصل احجز اي شي ابغاه الساعه 4 و نص العصر و اعطاني كتلوج المحل. لما الموظفين يتعاملو معاك باسلوب راقي رح ترجع مره و مرتين و ثلاثه!</body><path>D:\work\om\data\p\charlottes-jeddah\index.html</path><city>jeddah</city><date>2013-07-20 10:35:33.22 UTC</date></review>