<?xml version="1.0" ?><review><id>57799</id><useful>0</useful><authorId>1769481</authorId><authorName>مصطفى الصايغ</authorName><authorNOR>23</authorNOR><subject> باجة في جدة</subject><catogary> مأكولات وتسالي </catogary><rate>5</rate><body>من افضل المحلات في بيع كل انواع المكسرات دائمآ مكسراتهم طازجة ولذيذة بالاضافة الى افضل انواع القهوة اللي هم متخصصين باانتاجها اسعارهم جدآ مناسبة اللي فاكره الفصفص عندهم الكيلو بـ 21 ريال ويجي لذيذ جدآ واكثر شي احبه انهم يحطون المكسرات باكياس قابلة للفتح والاغلاق وكنها حافظة مو كيس .</body><path>D:\work\om\data\p\baja-jeddah\index.html</path><city>jeddah</city><date>2012-11-20 10:34:41.694 UTC</date></review>