<?xml version="1.0" ?><review><id>12413</id><useful>1</useful><authorId>1734292</authorId><authorName>هشام محمد</authorName><authorNOR>33</authorNOR><subject> حلويات سعد الدين في جدة</subject><catogary> مأكولات وتسالي </catogary><rate>5</rate><body>سعد الدين لديهم حلويات راقية جدآ انا حب البقلاوة اللي عندهم اكثر شي لانهم متميزين فيها اسعارهم اشوفها مناسبة جدآ خدمتهم ممتازة وتخللي الزبون يرجع لهم مرة تانية تعاملهم جدأ راقي يستحق التجربة وعن جدارة .</body><path>D:\work\om\data\p\saadeddin-sweets-4-jeddah\index.html</path><city>jeddah</city><date>2012-08-20 10:40:47.667 UTC</date></review>