<?xml version="1.0" ?><review><id>12806</id><useful>0</useful><authorId>6161</authorId><authorName>Nobody Nobody</authorName><authorNOR>81</authorNOR><subject> مخابز غيث في عمان</subject><catogary> مأكولات وتسالي </catogary><rate>3</rate><body>كان هادا المخبز المفضل عندي لما كنت ساكن في منطقة دوار الواحة. بتلاقي عنده كل أنواع الخبز و المعجنات الشركسية بس للأسف بتكون محضرة من فترة و بتتسخن بالمايكرويف :( المكان ضيق بالنسبة لعدد الزبائن الكبير خاصة أنه عرباية خبز الحمام الضخمة ماخدة مكان كبير على الفاضي بنص المحل. بالنسبة للمصافات صارت أحسن بعد ما أجروا تعديلات على رصيف دوار الواحة ، لكن سببوا مشكلة للمتجهين باتجاه شارع الجامعة و بطلوا يقدرو يصفوا عند المخبز بدون ما يدخلوا بعجقة الجاردنز.</body><path>D:\work\om\data\p\ghaith-bakery-3-amman\index.html</path><city>amman</city><date>2012-08-20 10:36:56.1 UTC</date></review>