<?xml version="1.0" ?><review><id>47097</id><useful>0</useful><authorId>1751656</authorId><authorName>סעד בולבול</authorName><authorNOR>14</authorNOR><subject> كرسبي كريم في الدمام</subject><catogary> مأكولات وتسالي </catogary><rate>5</rate><body>عروض جيده اسعار مناسبه موجود بكل مكان مثل المجمعات والشوارع عندهم عرض حلو مره 2 دونت وقهوه 8 ريال افصل شي عندهم الدونت الكلاسيك خطيييييييييييييييييييييييييييييييييييييييييييييييييييييييييييييييييييييييييييييييير</body><path>D:\work\om\data\p\krspy-kreme-5-dammam\index.html</path><city>dammam</city><date>2012-08-20 10:38:36.472 UTC</date></review>