<?xml version="1.0" ?><review><id>24755</id><useful>1</useful><authorId>551137</authorId><authorName>nadim farah 2011</authorName><authorNOR>157</authorNOR><subject> فرندز كيك في عمان</subject><catogary> مأكولات وتسالي </catogary><rate>4</rate><body>الكيك بالبوظة والتشيز كيك عنده زاكي ، اسعاره منيحة والمحل حلو ومرتب ونظيف ، شغلة مرتب وبيعمل تواصي وللمناسبات . خدمته جيدة وتعامل محترم :) جربوه :)</body><path>D:\work\om\data\p\friends-cake-amman\index.html</path><city>amman</city><date>2012-08-20 10:36:48.608 UTC</date></review>