<?xml version="1.0" ?><review><id>29675</id><useful>0</useful><authorId>1744168</authorId><authorName>نوف صالح</authorName><authorNOR>94</authorNOR><subject> دومينوز بيتزا في الدمام</subject><catogary> مطاعم </catogary><rate>5</rate><body>مطعم البيتزا المفضل عندي وماتوقع في احد يكره دومينوز العاجين عندهم انواع السميكه والرقيقه والمقرمشه انا احب الخفيفه والمقرمشه اكثر من السميكه ولو اطلب اي نوع من عندهم بوحده من هالعجينتين تطلع جنااااان والطعم الذ من السميكه احب الكيكرز مرررررره خصوصا مع الصوص الحار والبارد الي يحطونه الدبل ميلت حكابه لحالها الاسعار ماشي حالها الخدمه ممتازه بس يوم الاثنين انسوا انكم تقدرون تطلبون بالتيلفون من الزحمه لان يوم لاثنين عرضهم</body><path>D:\work\om\data\p\dominos-pizza-7-dammam\index.html</path><city>dammam</city><date>2012-08-20 10:36:20.158 UTC</date></review>