<?xml version="1.0" ?><review><id>66191</id><useful>0</useful><authorId>1781155</authorId><authorName>Khalid Alasmer</authorName><authorNOR>1</authorNOR><subject> لولو هايبرماركت في الرياض</subject><catogary> مأكولات وتسالي </catogary><rate>5</rate><body>مول متكامل من الظافه والإهتماام والأسعار المناسبه للجميع والعروض المتميزه والأكلات المتنوعه والجديده على الشارع العربي والمسابقات والجوائز والعروض المتميزه التي لم يختص بها اي مول اخر والمحلات لجميع الاطياف والحلويات لجميع المناسبات وبأسرع وقت ممكن وتوفر جميع انواع المحلات والكافيهات والمناظر الرائعه والتقنيات الحديثه باختصار كل ماتريده تجده وباقل الاسعار</body><path>D:\work\om\data\p\lulu-hypermarket-riyadh\index.html</path><city>riyadh</city><date>2013-04-20 10:38:54.859 UTC</date></review>