<?xml version="1.0" ?><review><id>71007</id><useful>1</useful><authorId>18086</authorId><authorName>nejoud bokhari</authorName><authorNOR>11</authorNOR><subject> لوست سيتي في جدة</subject><catogary> مقاهي وكوفي شوب </catogary><rate>1</rate><body>لوست ستي من اسؤ الاماكن في جده :/ الجلسات شبيها نوعا ما لروما كافية وبابايا كديكور وجو عام جميل االمكان الى ان تتذوق طعامهم . قائمة الماكولات متنوعه ولكن جودتها سيئة طلبنا اطباق رئيسية اتذكر طلبي مشويات وطعم اللحم سيء مثل الكباب المثلج وله رائحة غريبة طبعا مااكملت طبقي. طلبنا ايضا شوربة كريمة الدجاج يقدم في خبز و فوتوتشيني ومقبلات وفاهيتا كان الطبق اغلبة بصل طبق صدر دجاج بالكريمة معا خضار وبطاطا مهروسة طبعا الخدمه بطيئة ,, كان في طبق اخير ماكولات بحرية جات كل الاطباق واخويا اكل سلطة وشوربة وشوية مقبلات وطلبة ماجاء حتى كان يبغى يكنسل الطبق لانه شبع واخيرا جاء الطبق يوجد معسلات اسعارهم غالية مقارنة بطعم الطعام وخدمتهم السيئة كانت الخدمة 18 % الفاتورة 600 وشوية ,, اكيد الان اتلغت الخدمه في العيد جدا مزحوم وهناك انتظار وحجز يوجد اماكن للاصطفاف ,, وطبعا موقع المكان حلو قريب من الفنادق (كراون بلازا , والانتر) وقريب من اروما كافية من البحر ومركز جمجوم ~</body><path>D:\work\om\data\p\lost-city-jeddah\index.html</path><city>jeddah</city><date>2013-07-20 10:38:53.658 UTC</date></review>