<?xml version="1.0" ?><review><id>71849</id><useful>0</useful><authorId>1759082</authorId><authorName>الوعد الصادق</authorName><authorNOR>38</authorNOR><subject> مستوصف الأسرة الطبى في الرياض</subject><catogary> خدمات طبية </catogary><rate>5</rate><body>اكثر من رائع والكادر الطبي عندهم مرة متمكن من التخصصات حقاهم الدكتور محمد عندهم طب عام روعة مرة زين يشخص الحالة بكل دقة ويعطي المريض حقة بالمتابعة والمعاينة النظافة على اعلى مستوى وبعد وياليت انهم يوسعون المستوصف شوي لان دايم عندهم ازدحام رهيب انا احب الروح عندهم لان قبل علاج الجسد علاج الراحة النفسية</body><path>D:\work\om\data\p\al-ousra-medical-dispensary-riyadh\index.html</path><city>riyadh</city><date>2013-07-30 10:33:30.320 UTC</date></review>