<?xml version="1.0" ?><review><id>45348</id><useful>0</useful><authorId>1754489</authorId><authorName>اللهم اغفر لي وارحمني</authorName><authorNOR>10</authorNOR><subject> مستشفى حي الجامعة الخاص في جدة</subject><catogary> خدمات طبية </catogary><rate>2</rate><body>هذا المستشفى مستواه سيء من حيث الخدمات والاهتمام بالنظافة وخدمة المريض اما بالنسبة للاطباء فاجد انهم من اكفأ الاطباء ماشاء الله الواحد يستحمل سوء الخدمات علشان يتعالج تحت يد اطباء مثلهم لانهم والله خبرة وفاهمين شغلهم تعبت عند مرض ولدي عندهم لامبالاة بالمريض واهله من موظفين وموظفات الامن رحم الله واصبح شكلي مثل الشحاذ لانهم يرموني من مكان لمكان واتحملت علشان ابغى ولدي يتعالج عند دكتور شاطر وثقة والله خفت عليه من دكاترة هذي الايام كله تجارب والحمد لله سويت لولدي العمليه ونجحت وربي عافاه وسلمه والله يحفظنا ويحفظ عيالنا من كل مكروه ومن دخول كذا مستشفيات ... آآآآآمين</body><path>D:\work\om\data\p\university-hospital-district-special-jeddah\index.html</path><city>jeddah</city><date>2012-08-20 10:42:24.828 UTC</date></review>