<?xml version="1.0" ?><review><id>61082</id><useful>0</useful><authorId>1736768</authorId><authorName>رامي أبو فارس</authorName><authorNOR>10</authorNOR><subject> د. فراس غازي الصالح في عمان</subject><catogary> أطباء </catogary><rate>5</rate><body>من خلال تجربتا لاكثر الاسماء في مجال الامراض العصبية عند مرص احد افراد عائلتي، تبين ان الدكتور فراس الاكثر احتراف في الامراض العصبية، فهو شاب في منتصف الثلاثيتيات و مارس الطب و التخصص في اميركا و هو خريج جامعة MIS الشهيرة و لديه ممارسة في عيادات متخصصة في ALS و MS بل و مطلع دائم على الابحاث و العلاجات الجديدة، بالاضافة انه غير مادي و لا يتعاطى بالسمسرة كالغالب الاعظم في هذا المجال،</body><path>D:\work\om\data\p\dr-firas-ghazi-al-saleh-amman\index.html</path><city>amman</city><date>2013-01-20 10:36:25.422 UTC</date></review>