<?xml version="1.0" ?><review><id>61519</id><useful>0</useful><authorId>1774838</authorId><authorName>الشرسة لولو</authorName><authorNOR>1</authorNOR><subject> د. باسل محمد المشهراوي في عمان</subject><catogary> أطباء </catogary><rate>4</rate><body>بصراحة الدكتور باسل كتير ممتاز وانا عن تجربة بحكي عنه وكتير معاملته مع المرضى راقية ومتواضعة وانا بصراحة بنصح كل مريض انه ما يروح الا على الدكتور باسل لمعاملتة الراقية والمتواضعة ونصائحة المفيدة كمان</body><path>D:\work\om\data\p\dr-basil-mohamed-mashharawi-amman\index.html</path><city>amman</city><date>2013-01-20 10:36:22.482 UTC</date></review>