<?xml version="1.0" ?><review><id>42104</id><useful>0</useful><authorId>1751165</authorId><authorName>Laila Alshoaibi</authorName><authorNOR>9</authorNOR><subject> كبابجي في عمان</subject><catogary> مطاعم </catogary><rate>5</rate><body>مكان روعة وبرمضان كان من احلى وازكى الاماكن اللي افطرنا فيها ، بالرغم من الضغط اللي كان ، كان في متابعة مستمرة من اللي بيشتغلو وكان الاكل بنفس الجودة والقعدة ولا اروع ، انا شخصيا بنصح اي حدا يروح عليه لانه ماحيندم ، وبالنسبة للاسعار هي مش رخيصة بس كمان مش غالية ، يعني حسب الطلب بتقدر تحدد ، وعلى الخدمة والاكلات الطيبات مش خسارة فيه ، بتطلع وانتا شبعان ومبسوط وبدك ترجع مرة تانية كمان :)</body><path>D:\work\om\data\p\kabab-ji-amman\index.html</path><city>amman</city><date>2012-08-20 10:38:12.488 UTC</date></review>