<?xml version="1.0" ?><review><id>44460</id><useful>0</useful><authorId>6617</authorId><authorName>لين محمد</authorName><authorNOR>86</authorNOR><subject> بيت التنور في الخبر</subject><catogary> مطاعم </catogary><rate>5</rate><body>احبه حب مو طبيعي اكله مرره لذيذ وكميته زينه عندهم المقبلات الشرقيه خطييييييره و الاسمك والاكلات البحريه ممتازه الدجاج واللحم والروبيان السشواني لذييييذ انصحكم فيه والشوربات لا انساها جنااان الخدمه جيده والمكان مره نظيف الاسعار متوسطه الاكل مره يشبع ههههه</body><path>D:\work\om\data\p\bait-altanoor-khobar\index.html</path><city>khobar</city><date>2012-08-20 10:34:40.642 UTC</date></review>