<?xml version="1.0" ?><review><id>62251</id><useful>0</useful><authorId>1775600</authorId><authorName>Rateb Alkaialy 2012</authorName><authorNOR>351</authorNOR><subject> مكتب منصور الرشودى للخدمات العامة في الرياض</subject><catogary> سياحة وسفر </catogary><rate>4</rate><body>تعتبر من الشركات الرائدة فى تقديم خدمات العمرة والحج والتي تلتزم معك الى ااقصى حد ممكن بتقديم الخدمات الجيدة فى موسمي الحج والعمرة طبعا ماعدا بعض المواقف الخارجة عن الارادة خصوصا خلال موسم الحج</body><path>D:\work\om\data\p\mansour-al-rshoudi-general-service-office-riyadh\index.html</path><city>riyadh</city><date>2013-02-20 10:39:06.536 UTC</date></review>