<?xml version="1.0" ?><review><id>13321</id><useful>0</useful><authorId>2405</authorId><authorName>سوسن الخضير</authorName><authorNOR>54</authorNOR><subject> كنتاكي في عمان</subject><catogary> مطاعم </catogary><rate>4</rate><body>انا دايما بطلب من عندهم تشكن كرسبي كتيييييييييير زاكية وحارة واكلهم نظيف والمحل نظيف . اماكن الاصطفاف محدودة . خدمتهم سريعة والنادل كان كتير محترم. بنصحكم تجربوه</body><path>D:\work\om\data\p\kfc-4-amman\index.html</path><city>amman</city><date>2012-08-20 10:38:18.172 UTC</date></review>