<?xml version="1.0" ?><review><id>9367</id><useful>0</useful><authorId>1729068</authorId><authorName>احمد ابو جميل</authorName><authorNOR>3</authorNOR><subject> دي سيلفا في عمان</subject><catogary> مقاهي وكوفي شوب </catogary><rate>5</rate><body>انا مش عارف ليش ما في ناس حكين عن الكافية . يعنى هذا المحل كان بيتي من كثر ما كنت اعد فيه . و مع الديكور الجديد صار خيااااااااااااااااال الطاولات فيهم سمك و كتير حلو . جودة الطعام:ممتازة و جربوا جرلد شككن ليبانيز ستايل. خدمة الزبائن:نار. توفر خدمة الاصطفاف:يوجد. هل يقدم المشروبات الكحولية:لا. هل تنصح الاخرين بزيارته:نعم .</body><path>D:\work\om\data\p\de-silva-amman\index.html@page=2.html</path><city>amman</city><date>2012-08-20 10:36:08.600 UTC</date></review>