<?xml version="1.0" ?><review><id>45092</id><useful>3</useful><authorId>1754573</authorId><authorName>mohammad hammad</authorName><authorNOR>9</authorNOR><subject> جوستو في عمان</subject><catogary> مقاهي وكوفي شوب </catogary><rate>5</rate><body>من افضل الكوفي شوبات التي موجودة في المنطقة والتي تقوم على اساس وجود مطرب كل ليلة سهرته عائلية لا يوجد بها مشاكل مثل ما يحصل في كوفي شوبات اخرى اسعاره الشخص 10 دنانير كحد ادنى يقوم بطلب طلبات فيها يقوم بتقديم على كل طاولة المكسرات وفي رمضان الحلويات الرمضانية المسؤول عن الكافيه "سلطان" من افضل الاشخاص متساهل مع الجميع ولا يدع اي شخص بالخروج غير راضي يقوم بعمل مسابقات عدة واخر مسابقة كانت في رمضان على الفيسبوك على صفحة "الله يرحم جدك" حيث كل يوم كان هنالك سؤال سهل ومن يقوم بالاجابه عليه يربح سهرة لشخصين تتضمن ارجيلة و 2 سوفت درينك لكل شخص سهراته اكثر من رائعة كل يوم سهرة شكل يقومون بالتغيير دوما سهرة مصرية سهرة سورية سهرة عيد الحب وهكذا يقوم مطربين مشهورين بين الحين والاخر باحياء الليلة صاحب الكافيه شخص محترم يقوم دوما بالتحرك بين الطاولات ومعرفة اذا هنالك اي شكوى لتعديلها دوما كافيه في القمة النظافة : 5/5 الخدمة: 5/5 التعامل : 5/5</body><path>D:\work\om\data\p\gusto-amman\index.html</path><city>amman</city><date>2012-08-20 10:37:09.638 UTC</date></review>