<?xml version="1.0" ?><review><id>49500</id><useful>0</useful><authorId>88</authorId><authorName>عبير هشام ابو طوق</authorName><authorNOR>80</authorNOR><subject> كوشنز لاونج في عمان</subject><catogary> مقاهي وكوفي شوب </catogary><rate>5</rate><body>انا جربت المكان من يومين لما رحنا على بطلعة جماعية مع اعضاء وفريق جيران عمان، المكان جدا لطيف .. ديكوره كتير حلو .. الكنبايات جدا مريحة. الضيافة كانت مميزة .. ما تأخروا علينا ولا بطلبية مع انه العدد كان كبير (60) شخص .. حبيت عندهم عصير البرتقال كتير زاكي وفريش. جربت عندهم النسكافيه كمان .. زاكية :) الكوكيز كان زاكي كمان وجديد .. حبيته .. المكان اجمالا مرتب .. في قعدة جنب الشبك كتير حلوة خاصة بالصيف. بنصح فيه لعمل اجتماعات او قعدات جماعية :)</body><path>D:\work\om\data\p\cushions-lounge-amman\index.html</path><city>amman</city><date>2012-08-20 10:36:01.228 UTC</date></review>