<?xml version="1.0" ?><review><id>13379</id><useful>0</useful><authorId>2405</authorId><authorName>سوسن الخضير</authorName><authorNOR>54</authorNOR><subject> الزنبقة في عمان</subject><catogary> مأكولات وتسالي </catogary><rate>4</rate><body>افضل سوبر ماركت رحت عليه من ناحية البضاعة والنظافة والموظفيين المحترمين اسعارهم غالية شوي. اي شي بيجي عبالك بكون موجود عندهم. كتير المحل منظم</body><path>D:\work\om\data\p\al-zanbaka-amman\index.html</path><city>amman</city><date>2012-08-20 10:34:03.866 UTC</date></review>