<?xml version="1.0" ?><review><id>54066</id><useful>0</useful><authorId>1747126</authorId><authorName>omar kudsi</authorName><authorNOR>32</authorNOR><subject> مطعم برشلونة في عمان</subject><catogary> مطاعم </catogary><rate>4</rate><body>فكرة المطعم كتير حلوه.. صراحه أنا ما أكلت من عندو بس شربت مو عندو موز و حليب مع فراوله كتير زاكيه كانت بس شوي سكرها زياده بالنسبه لأسعار المطعم فهي طبيعيه مقاره بباقي المطاعم، نظافة المطعم ممتازه في محل مشان الواحد يقعد .. يعني بنصح الكل يجربه ما رح تندمو</body><path>D:\work\om\data\p\barcelona-amman\index.html</path><city>amman</city><date>2012-10-20 10:34:43.980 UTC</date></review>