<?xml version="1.0" ?><review><id>26537</id><useful>0</useful><authorId>1744417</authorId><authorName>منيره عبدالله</authorName><authorNOR>139</authorNOR><subject> شاهناز في الدمام</subject><catogary> مطاعم </catogary><rate>5</rate><body>مطعم بالفعل ممتاااز مع انه مو معروف كثير بس اكله رههيب المقبلات بكل انوعها لذيذ والاطباق الرئيسيه تحتار ايش تطلب برياني وكباب على كيف كيفك والباميه شي عجييييب الخدمه جدا ممتازه والقعده مرتبه ونظيفه وتفتح النفس الاسعار احلى شي عندهم لانك تاكل الين تشبع وتنصدم ان الفاتوره مو مرتفعه ابددد انصح الكل يحربه اكيد راح يعجبكم</body><path>D:\work\om\data\p\shahnaz-2-dammam\index.html</path><city>dammam</city><date>2012-08-20 10:41:12.778 UTC</date></review>