<?xml version="1.0" ?><review><id>67615</id><useful>0</useful><authorId>1782121</authorId><authorName>Raed Obaid</authorName><authorNOR>64</authorNOR><subject> مخازن البشيتي للادوات المنزلية في عمان</subject><catogary> أثاث ولوازم منزلية </catogary><rate>5</rate><body>فعلا من اروع الاماكن و اروع الاسعار و التشكيلات..التسوق فيه ممتع و فعلا كل ما تحتاجه موجود حتى شغلات ما بتخطر على البال بتلاقيها متوفرة عنده..انا بصراحة بفضل فرع شارع المدينة الطبية-صويلح اكثر من فرع خلدا لأنو أكبر و الاصطفاف فيه اسهل</body><path>D:\work\om\data\p\bashiti-stores-2-amman\index.html</path><city>amman</city><date>2013-05-20 10:34:44.832 UTC</date></review>