<?xml version="1.0" ?><review><id>64258</id><useful>1</useful><authorId>1776141</authorId><authorName>Ayman Hussain</authorName><authorNOR>24</authorNOR><subject> نعومي في جدة</subject><catogary> أزياء </catogary><rate>1</rate><body>تصاميم مبهرة وحلوة بس الخامة درجة ثالثة وماهي قد كده .. السعر مبالغ فيه مقارنة بالخامة وبالنهاية السعر موضوع على اساس انها ماركة معروفة ،،</body><path>D:\work\om\data\p\nayomi-29-jeddah\index.html</path><city>jeddah</city><date>2013-03-20 10:39:34.509 UTC</date></review>