<?xml version="1.0" ?><review><id>50083</id><useful>0</useful><authorId>1741309</authorId><authorName>فراس قاسم 2011</authorName><authorNOR>370</authorNOR><subject> حديقة الأردن للحيوان في عمان</subject><catogary> ترفيه </catogary><rate>3</rate><body>بروحها باستمرار وامبارح رحت عليها هيا بصراحة حلوة ومناسبة لجميع الاعمار لكن عيبها كما يلي: 1- الالعاب كتيرة بس مساحتها صغيرة وماعليها متابعة او رقابة وفي العاب مكسرة وخصوصا للاطفال وبالتالي لاسمح الله حال سقوط اي طفل من اللعبة من سيتحمل المسؤولية؟ 2- الحيوانات: حدث ولاحرج منظر محزن جدا للاسود والنمور بشكل خاص، الكآبة الواضحة على منظرهم من وضع العيشة المزرية والتي لايقبلها الانسان على نفسه ، صدقا سيئة جدا والمنظر يدل على وضع معيشي سيء جدا هناك حيوانات ايضا تعيش باقفاص صغيرة الحجم وهيا بحاجة لاقفاص اكبر مثل القرود والثعالب والذئاب 3- النظافة سيئ جدا ورائحة كريهة تنبعث من كل مكان في الحديثة وحتى انو والله رايت جرذ كبير يخرج من بين الاقفاص، وهاذ لو هجم على احد الاطفال لكان قد اذاه كثيرا؟ 4- اسعار الدخول مناسبة ولكن دون مقابل؟ اسعار الالعاب جيدا جدا ومناسبة جدا 5- الكوفي شوب والمطاعم موجودة وباسعار مناسبة 6- وجود بعض الشباب المشاكسين وهذا لايخدم الحديقة لانه سيؤدي لحدوث معاكسات ومشاكل مع الاهالي وشكرا</body><path>D:\work\om\data\p\jordan-garden-zoo-amman\index.html</path><city>amman</city><date>2012-08-20 10:38:08.143 UTC</date></review>