<?xml version="1.0" ?><review><id>50102</id><useful>0</useful><authorId>1741309</authorId><authorName>فراس قاسم 2011</authorName><authorNOR>370</authorNOR><subject> مجموعة ابو الحاج تاكسي المميز في عمان</subject><catogary> خدمات </catogary><rate>3</rate><body>بصراحة جربت اركب معهم مرة وجدة ومازبط الموضوع بالدباية حكالي انو رح يطلع العداد كتييييير تاني شي اصلا الشوفير يعني ما كان منيح بعدين مافي شي مميز عن غيرو متلو متل التاكسي العادي بالعكس اغلى بكتييييير خدمة التكيف بالتاكسي عادية وعلى الطلب</body><path>D:\work\om\data\p\abu-al-haj-group-al-moumayaz-taxi-amman\index.html</path><city>amman</city><date>2012-08-20 10:32:27.362 UTC</date></review>