<?xml version="1.0" ?><review><id>46770</id><useful>0</useful><authorId>1755816</authorId><authorName>الاء العطيات</authorName><authorNOR>4</authorNOR><subject> سيتي مول في عمان</subject><catogary> تسوق </catogary><rate>3</rate><body>بصراحة الستي مول انعش المنطقة وصار فيها حركة حلوة وبالنسبة للتسوق فيه طبعا رح يختلف من شخص لآخر كل واحد حسب احتياجاته وميزانيته .... يعني بالمختصر ممكن يناسب كل الناس بس طبعا بتفاوت حسب الاصناف أو الخدمات اللى بتحتاجها</body><path>D:\work\om\data\p\city-mall-amman\index.html@page=2.html</path><city>amman</city><date>2012-08-20 10:35:48.564 UTC</date></review>