<?xml version="1.0" ?><review><id>5403</id><useful>1</useful><authorId>12109</authorId><authorName>alsh5er2011</authorName><authorNOR>1</authorNOR><subject> برجر كنج في الرياض</subject><catogary> مطاعم </catogary><rate>4</rate><body>من ناحية النظافة والخدمة مافيه كلام الاحسن والاكل كمان ماعليه كلام بس بعض الايام يصير فيه زحمة شوي وموقعه كويس بس لو يصير فيه سرعه زيادة في تقديم الطلبات لأنو هذا هو السبب في الزحمة خدمة الزبائن هم في الخدمة توب توفر خدمة الاصطفاف فيها شوي يستحق السعر اللي دفعته وجودة الطعام اللي هي الاهم يمممم الاحلى هذي الصراحة وانا انصح اي واحد جيعان انه يزوره ......................!</body><path>D:\work\om\data\p\burger-king-5-riyadh\index.html</path><city>riyadh</city><date>2012-08-20 10:35:04.358 UTC</date></review>