<?xml version="1.0" ?><review><id>8434</id><useful>1</useful><authorId>11280</authorId><authorName>lama20112011</authorName><authorNOR>39</authorNOR><subject> فرايديز في الدمام</subject><catogary> مطاعم </catogary><rate>4</rate><body>انا اول ما كنت أحبه بس الفتره الأخيره تحسن اكلهم كثير و المنيو عندهم منوع.. الجلسات حلوه خاصه لجمعات البنات و الخدمه مره زينه.. أسعارهم متوسطه و النظافه كويسه..</body><path>D:\work\om\data\p\fridays-3-dammam\index.html</path><city>dammam</city><date>2012-08-20 10:36:48.101 UTC</date></review>